infi.multipathtools-0.1.40-py2.7-nspkg.pth
infi/multipathtools/__init__.py
infi/multipathtools/__version__.py
infi/multipathtools/client/__init__.py
infi/multipathtools/client/tests.py
infi/multipathtools/config/__init__.py
infi/multipathtools/config/sample.txt
infi/multipathtools/config/tests.py
infi/multipathtools/connection/__init__.py
infi/multipathtools/connection/tests.py
infi/multipathtools/dtypes/__init__.py
infi/multipathtools/errors/__init__.py
infi/multipathtools/model/__init__.py
infi/multipathtools/model/scripts.py
infi/multipathtools/model/tests.py
infi/multipathtools/scripts/__init__.py
infi/multipathtools/service/__init__.py
infi/multipathtools/service/tests.py
infi/multipathtools/simulator/__init__.py
infi/multipathtools/simulator/examples.txt
infi.multipathtools-0.1.40.dist-info/LICENSE
infi.multipathtools-0.1.40.dist-info/METADATA
infi.multipathtools-0.1.40.dist-info/WHEEL
infi.multipathtools-0.1.40.dist-info/entry_points.txt
infi.multipathtools-0.1.40.dist-info/namespace_packages.txt
infi.multipathtools-0.1.40.dist-info/top_level.txt
infi.multipathtools-0.1.40.dist-info/RECORD
