Metadata-Version: 2.1
Name: infi.multipathtools
Version: 0.1.40
Summary: python bindings to multipath-tools daemon
Home-page: https://github.com/Infinidat/infi.multipathtools
Author: Arnon Yaari
Author-email: arnony@infinidat.com
License: BSD
Platform: UNKNOWN
Classifier: Intended Audience :: Developers
Classifier: Intended Audience :: System Administrators
Classifier: License :: OSI Approved :: BSD License
Classifier: Operating System :: OS Independent
Classifier: Programming Language :: Python
Classifier: Programming Language :: Python :: 2
Classifier: Programming Language :: Python :: 3
Classifier: Topic :: Software Development :: Libraries :: Python Modules
Requires-Dist: infi.exceptools
Requires-Dist: infi.execute
Requires-Dist: infi.instruct
Requires-Dist: infi.pyutils
Requires-Dist: munch
Requires-Dist: setuptools
Requires-Dist: six
